Workbook

Sheet LEAD
B2: XBRL CoE Checklist
B3: ※ XBRL Checklist 결과는 참고 목적으로 제공드리는 내역으로, 텍사노미 구조와 관련된 리뷰는 CoE 업무 Scope에 포함되지 않습니다.
B11: ="Total"&" : "&SUM(N14:N51) -> Total : 0 | C11: 개 항목이 추출되었습니다.
B13: # | C13: 항목 | D13: 세부내역 | N13: 검출항목
B14: 1 | C14: 특정요소 사용검토 | D14: • 총액계정 사용 검토 | N14: ='Checklist_1-1'!B11 -> 0
D15: • 초과적립액(과소적립액) | N15: ='Checklist_1-2'!B11 -> 0
D16: • 재고자산 세부내역 표 | N16: ='Checklist_1-3'!B11 -> 0
D17: • 유동/비유동 축 | N17: ='Checklist_1-4'!B11 -> 0
B18: 2 | C18: 택사노미 검토 | D18: • 금융자산의 대손충당금 (만료 텍사노미 검토) | N18: ='Checklist_2-1'!B11 -> 0
D19: • 금융자산의 손상차손 축 (만료 텍사노미 검토) | N19: ='Checklist_2-2'!B11 -> 0
D20: • 대출약정금액 텍사노미 검토 | N20: ='Checklist_2-3'!B11 -> 0
D21: • 미착품 택사노미 검토 | N21: ='Checklist_2-4'!B11 -> 0
D22: • 배당금 텍사노미 검토 | N22: ='Checklist_2-5'!$B$11 -> 0
D23: • 평균유효세율 택사노미 검토 (분반기) | N23: ='Checklist_2-6'!$B$11 -> 0
B24: 3 | C24: 축-멤버 정합성 검토 | D24: • 표준 축-멤버 구조 정합성 | N24: ='Checklist_3-1'!B11 -> 0
D25: • 공시금액의 사용 적정성 | N25: ='Checklist_3-2'!B11 -> 0
B26: 4 | C26: 전용요소 사용 검토 | D26: • 현금흐름 관련 표 내에서 다른 요소 사용 | N26: ='Checklist_4-1'!B11 -> 0
D27: • 현금흐름 관련 표의 전용요소가 다른 표에서 사용 | N27: ='Checklist_4-2'!B11 -> 0
D28: • 판매관리비 관련 표내에서 다른 요소 사용 | N28: ='Checklist_4-3'!B11 -> 0
D29: • 판매비와관리비 관련 표의 전용요소가 다른 표에서 사용 | N29: ='Checklist_4-4'!B11 -> 0
D30: • 특수관계자 관련 표 내에서 다른 요소 사용 | N30: ='Checklist_4-5'!B11 -> 0
D31: • 특수관계자 관련 표의 전용요소가 다른 표에서 사용 | N31: ='Checklist_4-6'!B11 -> 0
B32: 5 | C32: 속성/데이터타입 검토 | D32: • Percent 소숫점 자리수 검토 | N32: ='Checklist_5-1'!B11 -> 0
D33: • 보유하는 주식수 속성 검토 | N33: ='Checklist_5-2'!B11 -> 0
D34: • 이연법인세부채(자산)은 텍사노미 및 부호 검토 | N34: ='Checklist_5-3'!B11 -> 0
D35: • 기본주당이익/희석주당이익 속성 검토 | N35: ='Checklist_5-4'!B11 -> 0
D36: • 기초/기말 영문명 검토 | N36: ='Checklist_5-5'!B11 -> 0
B37: 6 | C37: 확장 검토 | D37: • 축 확장 검토 | N37: ='Checklist_6-1'!B11 -> 0
D38: • 멤버 합계열 적절성 검토 | N38: ='Checklist_6-2'!B11 -> 0
D39: • Duration / Instant 속성 검토 | N39: ='Checklist_6-3'!B11 -> 0
D40: • negated 검토 | N40: ='Checklist_7-1'!B11 -> 0
B45: 7 | C45: 기타

Sheet Checklist_1-1
B2: 총액계정 사용 검토
B3: ※ XBRL Checklist 결과는 참고 목적으로 제공드리는 내역으로, 텍사노미 구조와 관련된 리뷰는 CoE 업무 Scope에 포함되지 않습니다.
L4: Reference - 금감원 가이드 86page
B11: =COUNTA(B14:B1048576) -> 0 | C11: 개 항목이 추출되었습니다.
B13: Role Definition | C13: TABLE NAME | D13: Prefix | E13: Name | F13: Label(KO) | G13: Label(EN) | H13: Label Role | I13: DataType | J13: Period
B14: [D831150] 4. 건설계약 등 | 4. Construction Contracts | C14: 도급공사계약과 관련한 주요 자산 및 부채에 대한 공시 | D14: dart | E14: ReceivablesOnConstructionContracts | F14: 공사미수금(*2) | G14: Receivables On construction contracts(*2) | H14: http://dart.fss.or.kr/role/2024-06-30/ifrs/dart_label | I14: monetaryItemType | J14: INSTANT
B15: [D831150] 4. 건설계약 등 | 4. Construction Contracts | C15: 도급공사계약과 관련한 주요 자산 및 부채에 대한 공시 | D15: dart | E15: LongTermTradeReceivablesGross | F15: 장기채권 | G15: Long-term receivables | H15: http://dart.fss.or.kr/role/2024-06-30/ifrs/dart_label | I15: monetaryItemType | J15: INSTANT
B16: [D831150] 4. 건설계약 등 | 4. Construction Contracts | C16: 도급공사계약과 관련한 주요 자산 및 부채에 대한 공시 | D16: dart | E16: ShortTermLoans | F16: 단기대여금 | G16: Short-term loans | H16: http://dart.fss.or.kr/role/2024-06-30/ifrs/dart_label | I16: monetaryItemType | J16: INSTANT
B17: [D831155] 4. 건설계약 등 | 4. Construction Contracts | C17: 도급공사계약과 관련한 주요 자산 및 부채에 대한 공시 | D17: dart | E17: ReceivablesOnConstructionContracts | F17: 공사미수금(*2) | G17: Receivables On construction contracts(*2) | H17: http://dart.fss.or.kr/role/2024-06-30/ifrs/dart_label | I17: monetaryItemType | J17: INSTANT
B18: [D831155] 4. 건설계약 등 | 4. Construction Contracts | C18: 도급공사계약과 관련한 주요 자산 및 부채에 대한 공시 | D18: dart | E18: LongTermTradeReceivablesGross | F18: 장기채권 | G18: Long-term receivables | H18: http://dart.fss.or.kr/role/2024-06-30/ifrs/dart_label | I18: monetaryItemType | J18: INSTANT
B19: [D831155] 4. 건설계약 등 | 4. Construction Contracts | C19: 도급공사계약과 관련한 주요 자산 및 부채에 대한 공시 | D19: dart | E19: ShortTermLoans | F19: 단기대여금 | G19: Short-term loans | H19: http://dart.fss.or.kr/role/2024-06-30/ifrs/dart_label | I19: monetaryItemType | J19: INSTANT

Sheet Checklist_1-2
B2: 초과적립액(과소적립액) 텍사노미 사용 검토
B3: ※ XBRL Checklist 결과는 참고 목적으로 제공드리는 내역으로, 텍사노미 구조와 관련된 리뷰는 CoE 업무 Scope에 포함되지 않습니다.
L4: Reference - 금감원 가이드 228page
B11: =COUNTA(B14:B1048576) -> 0 | C11: 개 항목이 추출되었습니다.
B13: Role Definition | C13: TABLE NAME | D13: Prefix | E13: Name | F13: Label(KO) | G13: Label(EN) | H13: Label Role | I13: DataType | J13: Period
B14: [D834480] 15. 순확정급여부채 | 15. Net Defined Benefit Liabilities(Assets) | C14: 확정급여제도에 대한 공시 | D14: ifrs-full | E14: SurplusDeficitInPlan | F14: 차감계 | G14: Defined benefit obligation | H14: http://www.xbrl.org/2009/role/negatedLabel | I14: monetaryItemType | J14: INSTANT
B15: [D834485] 15. 순확정급여부채 | 15. Net Defined Benefit Liabilities(Assets) | C15: 확정급여제도에 대한 공시 | D15: ifrs-full | E15: SurplusDeficitInPlan | F15: 차감계 | G15: Defined benefit obligation | H15: http://www.xbrl.org/2009/role/negatedLabel | I15: monetaryItemType | J15: INSTANT

Sheet Checklist_1-3
B2: 재고자산 세부내역 표 검토
B3: ※ XBRL Checklist 결과는 참고 목적으로 제공드리는 내역으로, 텍사노미 구조와 관련된 리뷰는 CoE 업무 Scope에 포함되지 않습니다.
B11: =COUNTA(B14:B1048576) -> 0 | C11: 개 항목이 추출되었습니다.
B13: Role Definition | C13: TABLE NAME | D13: Prefix | E13: Name | F13: Label(KO) | G13: Label(EN) | H13: Label Role | I13: DataType | J13: Period

Sheet Checklist_1-4
B2: 유동/비유동 축 검토
B3: ※ XBRL Checklist 결과는 참고 목적으로 제공드리는 내역으로, 텍사노미 구조와 관련된 리뷰는 CoE 업무 Scope에 포함되지 않습니다.
B11: =COUNTA(B14:B1048576) -> 0 | C11: 개 항목이 추출되었습니다.
B13: Role Definition | C13: TABLE NAME | D13: Prefix | E13: Name | F13: Label(KO) | G13: Label(EN) | H13: Label Role | I13: DataType | J13: Period

Sheet Checklist_2-1
B2: 만료 택사노미 검토 - 대손충당금
B3: ※ XBRL Checklist 결과는 참고 목적으로 제공드리는 내역으로, 텍사노미 구조와 관련된 리뷰는 CoE 업무 Scope에 포함되지 않습니다.
B11: =COUNTA(B14:B1048576) -> 0 | C11: 개 항목이 추출되었습니다.
B13: Role Definition | C13: TABLE NAME | D13: Prefix | E13: Name | F13: Label(KO) | G13: Label(EN) | H13: Label Role | I13: DataType | J13: Period

Sheet Checklist_2-2
B2: 만료 택사노미 검토 - 손상차손 축
B3: ※ XBRL Checklist 결과는 참고 목적으로 제공드리는 내역으로, 텍사노미 구조와 관련된 리뷰는 CoE 업무 Scope에 포함되지 않습니다.
B11: =COUNTA(B14:B1048576) -> 0 | C11: 개 항목이 추출되었습니다.
B13: Role Definition | C13: TABLE NAME | D13: Prefix | E13: Name | F13: Label(KO) | G13: Label(EN) | H13: Label Role | I13: DataType | J13: Period

Sheet Checklist_2-3
B2: 택사노미 검토 - 대출약정금액
B3: ※ XBRL Checklist 결과는 참고 목적으로 제공드리는 내역으로, 텍사노미 구조와 관련된 리뷰는 CoE 업무 Scope에 포함되지 않습니다.
B11: =COUNTA(B14:B1048576) -> 0 | C11: 개 항목이 추출되었습니다.
B13: Role Definition | C13: TABLE NAME | D13: Prefix | E13: Name | F13: Label(KO) | G13: Label(EN) | H13: Label Role | I13: DataType | J13: Period

Sheet Checklist_2-4
B2: 택사노미 검토 - 미착품
B3: ※ XBRL Checklist 결과는 참고 목적으로 제공드리는 내역으로, 텍사노미 구조와 관련된 리뷰는 CoE 업무 Scope에 포함되지 않습니다.
B11: =COUNTA(B14:B1048576) -> 0 | C11: 개 항목이 추출되었습니다.
B13: Role Definition | C13: TABLE NAME | D13: Prefix | E13: Name | F13: Label(KO) | G13: Label(EN) | H13: Label Role | I13: DataType | J13: Period

Sheet Checklist_2-5
B2: 택사노미 검토 - 배당금
B3: ※ XBRL Checklist 결과는 참고 목적으로 제공드리는 내역으로, 텍사노미 구조와 관련된 리뷰는 CoE 업무 Scope에 포함되지 않습니다.
B11: =COUNTA(B14:B1048576) -> 0 | C11: 개 항목이 추출되었습니다.
B13: Role Definition | C13: TABLE NAME | D13: Prefix | E13: Name | F13: Label(KO) | G13: Label(EN) | H13: Label Role | I13: DataType | J13: Period
B14: [D610000] 자본변동표 - 연결 | Statement of changes in equity - Consolidated financial statements | C14: [D610000] 자본변동표 - 연결 | D14: ifrs-full | E14: DividendsPaid | F14: 배당 | G14: Dividends paid | H14: http://www.xbrl.org/2009/role/negatedTerseLabel | I14: monetaryItemType | J14: DURATION
B15: [D610000] 자본변동표 - 연결 | Statement of changes in equity - Consolidated financial statements | C15: [D610000] 자본변동표 - 연결 | D15: ifrs-full | E15: DividendsPaid | F15: 배당 | G15: Dividends paid | H15: http://www.xbrl.org/2009/role/negatedTerseLabel | I15: monetaryItemType | J15: DURATION
B16: [D610000] 자본변동표 - 연결 | Statement of changes in equity - Consolidated financial statements | C16: [D610000] 자본변동표 - 연결 | D16: ifrs-full | E16: DividendsPaid | F16: 배당 | G16: Dividends paid | H16: http://www.xbrl.org/2009/role/negatedTerseLabel | I16: monetaryItemType | J16: DURATION
B17: [D610005] 자본변동표 - 별도 | Statement of changes in equity - Separate financial statements | C17: [D610005] 자본변동표 - 별도 | D17: ifrs-full | E17: DividendsPaid | F17: 배당 | G17: Dividends paid | H17: http://www.xbrl.org/2009/role/negatedTerseLabel | I17: monetaryItemType | J17: DURATION
B18: [D610005] 자본변동표 - 별도 | Statement of changes in equity - Separate financial statements | C18: [D610005] 자본변동표 - 별도 | D18: ifrs-full | E18: DividendsPaid | F18: 배당 | G18: Dividends paid | H18: http://www.xbrl.org/2009/role/negatedTerseLabel | I18: monetaryItemType | J18: DURATION
B19: [D610005] 자본변동표 - 별도 | Statement of changes in equity - Separate financial statements | C19: [D610005] 자본변동표 - 별도 | D19: ifrs-full | E19: DividendsPaid | F19: 배당 | G19: Dividends paid | H19: http://www.xbrl.org/2009/role/negatedTerseLabel | I19: monetaryItemType | J19: DURATION
B20: [D861305] 20. 이익잉여금 | 20. Separated retained earnings | C20: 이익잉여금 처분계산서 | D20: ifrs-full | E20: DividendsProposedOrDeclaredBeforeFinancialStatementsAuthorisedForIssueButNotRecognisedAsDistributionToOwners | F20: 재무제표 발행승인일 전에 제안 또는 선언되었으나 당해 기간 동안에 소유주에 대한 분배금으로 인식되지 아니한 배당금 | G20: Dividends proposed or declared before financial statements authorised for issue but not recognised as distribution to owners | H20: http://www.xbrl.org/2003/role/label | I20: monetaryItemType | J20: DURATION
B21: [D861305] 20. 이익잉여금 | 20. Separated retained earnings | C21: 이익잉여금 처분계산서 | D21: ifrs-full | E21: DividendsPaidOrdinarySharesPerShare | F21: 보통주에 지급된 주당배당금 | G21: Dividends paid, ordinary shares per share | H21: http://www.xbrl.org/2003/role/label | I21: perShareItemType | J21: DURATION
B22: [D861305] 20. 이익잉여금 | 20. Separated retained earnings | C22: 이익잉여금 처분계산서 | D22: dart | E22: DividendsPaidPreferredSharesPerShare | F22: 우선주에 지급된 주당배당금 | G22: Dividends paid, preferred shares per share | H22: http://www.xbrl.org/2003/role/label | I22: perShareItemType | J22: DURATION
B23: [D861305] 20. 이익잉여금 | 20. Separated retained earnings | C23: 이익잉여금 처분계산서 | D23: dart | E23: DividendsPayableOrdinarySharesPerShare | F23: 보통주에 지급될 주당배당금 | G23: Dividends payable, ordinary shares per share | H23: http://www.xbrl.org/2003/role/label | I23: perShareItemType | J23: DURATION
B24: [D861305] 20. 이익잉여금 | 20. Separated retained earnings | C24: 이익잉여금 처분계산서 | D24: dart | E24: DividendsPayablePreferredSharesPerShare | F24: 우선주에 지급될 주당배당금 | G24: Dividends payable, preferred shares per share | H24: http://www.xbrl.org/2003/role/label | I24: perShareItemType | J24: DURATION

Sheet Checklist_2-6
B2: 택사노미 검토 - 평균유효세율
B3: ※ XBRL Checklist 결과는 참고 목적으로 제공드리는 내역으로, 텍사노미 구조와 관련된 리뷰는 CoE 업무 Scope에 포함되지 않습니다.
B11: =COUNTA(B14:B1048576) -> 0 | C11: 개 항목이 추출되었습니다.
B13: Role Definition | C13: TABLE NAME | D13: Prefix | E13: Name | F13: Label(KO) | G13: Label(EN) | H13: Label Role | I13: DataType | J13: Period

Sheet Checklist_3-1
B2: 축-멤버 구조 정합성 검토
B3: ※ XBRL Checklist 결과는 참고 목적으로 제공드리는 내역으로, 텍사노미 구조와 관련된 리뷰는 CoE 업무 Scope에 포함되지 않습니다.
B11: =COUNTA(B14:B1048576) -> 0 | C11: 개 항목이 추출되었습니다.
B13: Role Definition | C13: TABLE NAME | D13: Prefix | E13: Name | F13: Label(KO) | G13: Label(EN) | H13: Label Role | I13: DataType | J13: Period
B14: [D822380] 30-1. 재무위험관리 | 30-1. Financial Risk Management | C14: 충당금 설정률표에 대한 공시 | D14: ifrs-full | E14: NotLaterThanThreeMonthsMember | F14: 90일 이내 연체 및 정상채권 | G14: Not later than three months | H14: http://www.xbrl.org/2003/role/terseLabel | I14: domainItemType | J14: DURATION
B15: [D822380] 30-1. 재무위험관리 | 30-1. Financial Risk Management | C15: 충당금 설정률표에 대한 공시 | D15: ifrs-full | E15: LaterThanThreeMonthsAndNotLaterThanSixMonthsMember | F15: 180일 이내 연체 | G15: Later than three months and not later than six months | H15: http://www.xbrl.org/2003/role/terseLabel | I15: domainItemType | J15: DURATION
B16: [D822380] 30-1. 재무위험관리 | 30-1. Financial Risk Management | C16: 충당금 설정률표에 대한 공시 | D16: ifrs-full | E16: LaterThanOneYearMember | F16: 1년 초과 연체 | G16: Later than one year | H16: http://www.xbrl.org/2003/role/terseLabel | I16: domainItemType | J16: DURATION
B17: [D822385] 30-1. 재무위험관리 | 30-1. Financial Risk Management | C17: 충당금 설정률표에 대한 공시 | D17: ifrs-full | E17: NotLaterThanThreeMonthsMember | F17: 90일 이내 연체 및 정상채권 | G17: Not later than three months | H17: http://www.xbrl.org/2003/role/terseLabel | I17: domainItemType | J17: DURATION
B18: [D822385] 30-1. 재무위험관리 | 30-1. Financial Risk Management | C18: 충당금 설정률표에 대한 공시 | D18: ifrs-full | E18: LaterThanThreeMonthsAndNotLaterThanSixMonthsMember | F18: 180일 이내 연체 | G18: Later than three months and not later than six months | H18: http://www.xbrl.org/2003/role/terseLabel | I18: domainItemType | J18: DURATION
B19: [D822385] 30-1. 재무위험관리 | 30-1. Financial Risk Management | C19: 충당금 설정률표에 대한 공시 | D19: ifrs-full | E19: LaterThanOneYearMember | F19: 1년 초과 연체 | G19: Later than one year | H19: http://www.xbrl.org/2003/role/terseLabel | I19: domainItemType | J19: DURATION
B20: [D822420] 7-1. 매출채권 및 기타자산 | 7-1. Trade Receivables and Other Assets | C20: 매출채권 및 기타자산의 공시 | D20: ifrs-full | E20: ClassesOfFinancialInstrumentsMember | F20: 금융상품 [구성요소] | G20: Financial instruments, class [member] | H20: http://www.xbrl.org/2003/role/label | I20: domainItemType | J20: DURATION
B21: [D822425] 7-1. 매출채권 및 기타자산 | 7-1. Trade Receivables and Other Assets | C21: 매출채권 및 기타자산의 공시 | D21: ifrs-full | E21: ClassesOfFinancialInstrumentsMember | F21: 금융상품 [구성요소] | G21: Financial instruments, class [member] | H21: http://www.xbrl.org/2003/role/label | I21: domainItemType | J21: DURATION
B22: [D822430] 6-1. 범주별 금융상품 | 6-1. Financial Instruments by Category | C22: 금융상품의 범주별 순손익 구분 | D22: dart | E22: OtherFinancialAssetsMember | F22: 매출채권 관련 | G22: Related to accounts receivables | H22: http://www.xbrl.org/2003/role/terseLabel | I22: domainItemType | J22: DURATION
B23: [D822435] 6-1. 범주별 금융상품 | 6-1. Financial Instruments by Category | C23: 금융상품의 범주별 순손익 구분 | D23: dart | E23: OtherFinancialAssetsMember | F23: 매출채권 관련 | G23: Related to accounts receivables | H23: http://www.xbrl.org/2003/role/terseLabel | I23: domainItemType | J23: DURATION
B24: [D822435] 6-1. 범주별 금융상품 | 6-1. Financial Instruments by Category | C24: 금융상품의 범주별 순손익 구분 | D24: ifrs-full | E24: FinancialGuaranteeContractsMember | F24: 금융보증부채 | G24: Financial guarantee liabilities | H24: http://www.xbrl.org/2003/role/terseLabel | I24: domainItemType | J24: DURATION
... B75: [D851105] 28. 현금흐름표 | 28. Separated Statements of Cash Flows | C75: 재무활동현금흐름 | D75: dart | E75: BondsIssuedMember | F75: 사채 [구성요소] | G75: Bonds issued [member] | H75: http://www.xbrl.org/2003/role/label | I75: domainItemType | J75: DURATION

Sheet Checklist_3-2
B2: 공시금액의 사용 적정성 검토
B3: ※ XBRL Checklist 결과는 참고 목적으로 제공드리는 내역으로, 텍사노미 구조와 관련된 리뷰는 CoE 업무 Scope에 포함되지 않습니다.
L4: Reference - 금감원 가이드 137page
B11: =COUNTA(B14:B1048576) -> 0 | C11: 개 항목이 추출되었습니다.
B13: Role Definition | C13: TABLE NAME | D13: Prefix | E13: Name | F13: Label(KO) | G13: Label(EN) | H13: Label Role | I13: DataType | J13: Period

Sheet Checklist_4-1
B2: 현금흐름표 관련 전용요소 검토 (1)
B3: ※ XBRL Checklist 결과는 참고 목적으로 제공드리는 내역으로, 텍사노미 구조와 관련된 리뷰는 CoE 업무 Scope에 포함되지 않습니다.
L4: Reference - 금감원 가이드 158page
B11: =COUNTA(B14:B1048576) -> 0 | C11: 개 항목이 추출되었습니다.
B13: Role Definition | C13: TABLE NAME | D13: Prefix | E13: Name | F13: Label(KO) | G13: Label(EN) | H13: Label Role | I13: DataType | J13: Period
B14: [D851100] 28. 연결현금흐름표 | 28. Consolidated Statements of Cash Flows | C14: 영업으로부터 창출된 현금 | D14: dart | E14: ExpenseOfProvisionForConstructionLosses | F14: 공사손실충당부채전입 | G14: Expense of provision for construction losses | H14: http://www.xbrl.org/2003/role/terseLabel | I14: monetaryItemType | J14: DURATION
B15: [D851100] 28. 연결현금흐름표 | 28. Consolidated Statements of Cash Flows | C15: 영업으로부터 창출된 현금 | D15: dart | E15: ExpenseOfProvisionForConstructionWarranty | F15: 하자보수충당부채전입 | G15: Expense of provision for construction warranty | H15: http://www.xbrl.org/2003/role/terseLabel | I15: monetaryItemType | J15: DURATION
B16: [D851100] 28. 연결현금흐름표 | 28. Consolidated Statements of Cash Flows | C16: 영업으로부터 창출된 현금 | D16: dart | E16: ReversalsOfProvisionsForConstructionLosses | F16: 공사손실충당부채환입 | G16: Reversals of provisions for construction losses | H16: http://www.xbrl.org/2009/role/negatedLabel | I16: monetaryItemType | J16: DURATION
B17: [D851105] 28. 현금흐름표 | 28. Separated Statements of Cash Flows | C17: 영업으로부터 창출된 현금 | D17: dart | E17: ExpenseOfProvisionForConstructionLosses | F17: 공사손실충당부채전입 | G17: Expense of provision for construction losses | H17: http://www.xbrl.org/2003/role/terseLabel | I17: monetaryItemType | J17: DURATION
B18: [D851105] 28. 현금흐름표 | 28. Separated Statements of Cash Flows | C18: 영업으로부터 창출된 현금 | D18: dart | E18: ExpenseOfProvisionForConstructionWarranty | F18: 하자보수충당부채전입 | G18: Expense of provision for construction warranty | H18: http://www.xbrl.org/2003/role/terseLabel | I18: monetaryItemType | J18: DURATION
B19: [D851105] 28. 현금흐름표 | 28. Separated Statements of Cash Flows | C19: 영업으로부터 창출된 현금 | D19: dart | E19: ReversalsOfProvisionsForConstructionLosses | F19: 공사손실충당부채환입 | G19: Reversals of provisions for construction losses | H19: http://www.xbrl.org/2009/role/negatedLabel | I19: monetaryItemType | J19: DURATION

Sheet Checklist_4-2
B2: 현금흐름표 관련 전용요소 검토 (2)
B3: ※ XBRL Checklist 결과는 참고 목적으로 제공드리는 내역으로, 텍사노미 구조와 관련된 리뷰는 CoE 업무 Scope에 포함되지 않습니다.
B11: =COUNTA(B14:B1048576) -> 0 | C11: 개 항목이 추출되었습니다.
B13: Role Definition | C13: TABLE NAME | D13: Prefix | E13: Name | F13: Label(KO) | G13: Label(EN) | H13: Label Role | I13: DataType | J13: Period

Sheet Checklist_4-3
B2: 판매비와관리비 관련 전용요소 검토 (1)
B3: ※ XBRL Checklist 결과는 참고 목적으로 제공드리는 내역으로, 텍사노미 구조와 관련된 리뷰는 CoE 업무 Scope에 포함되지 않습니다.
L4: Reference - 금감원 가이드 157page
B11: =COUNTA(B14:B1048576) -> 0 | C11: 개 항목이 추출되었습니다.
B13: Role Definition | C13: TABLE NAME | D13: Prefix | E13: Name | F13: Label(KO) | G13: Label(EN) | H13: Label Role | I13: DataType | J13: Period

Sheet Checklist_4-4
B2: 판매비와관리비 관련 전용요소 검토 (2)
B3: ※ XBRL Checklist 결과는 참고 목적으로 제공드리는 내역으로, 텍사노미 구조와 관련된 리뷰는 CoE 업무 Scope에 포함되지 않습니다.
B11: =COUNTA(B14:B1048576) -> 0 | C11: 개 항목이 추출되었습니다.
B13: Role Definition | C13: TABLE NAME | D13: Prefix | E13: Name | F13: Label(KO) | G13: Label(EN) | H13: Label Role | I13: DataType | J13: Period

Sheet Checklist_4-5
B2: 특수관계자 관련 전용요소 검토 (1)
B3: ※ XBRL Checklist 결과는 참고 목적으로 제공드리는 내역으로, 텍사노미 구조와 관련된 리뷰는 CoE 업무 Scope에 포함되지 않습니다. | L3: Reference - 금감원 가이드 158page
B11: =COUNTA(B14:B1048576) -> 0 | C11: 개 항목이 추출되었습니다.
B13: Role Definition | C13: TABLE NAME | D13: Prefix | E13: Name | F13: Label(KO) | G13: Label(EN) | H13: Label Role | I13: DataType | J13: Period
B14: [D818000] 27. 특수관계자등과의 거래 | 27. Related Party Transactions | C14: 특수관계자와 기업의 보증이나 담보의 제공에 대한 공시 | D14: dart | E14: GuaranteeProvider | F14: 보증처 | G14: Guarantee provider | H14: http://www.xbrl.org/2003/role/label | I14: stringItemType | J14: DURATION
B15: [D818000] 27. 특수관계자등과의 거래 | 27. Related Party Transactions | C15: 약정에 대한 공시_특수관계자 | D15: dart | E15: DescriptionOfCommitments | F15: 약정에 대한 설명 | G15: Description of commitments | H15: http://www.xbrl.org/2003/role/label | I15: stringItemType | J15: DURATION
B16: [D818005] 27. 특수관계자등과의 거래 | 27. Related Party Transactions | C16: 특수관계자와 기업의 보증이나 담보의 제공에 대한 공시 | D16: dart | E16: GuaranteeProvider | F16: 보증처 | G16: Guarantee provider | H16: http://www.xbrl.org/2003/role/label | I16: stringItemType | J16: DURATION
B17: [D818005] 27. 특수관계자등과의 거래 | 27. Related Party Transactions | C17: 약정에 대한 공시_특수관계자 | D17: dart | E17: DescriptionOfCommitments | F17: 약정에 대한 설명 | G17: Description of commitments | H17: http://www.xbrl.org/2003/role/label | I17: stringItemType | J17: DURATION

Sheet Checklist_4-6
B2: 특수관계자 관련 전용요소 검토 (2)
B3: ※ XBRL Checklist 결과는 참고 목적으로 제공드리는 내역으로, 텍사노미 구조와 관련된 리뷰는 CoE 업무 Scope에 포함되지 않습니다.
B11: =COUNTA(B14:B1048576) -> 0 | C11: 개 항목이 추출되었습니다.
B13: Role Definition | C13: TABLE NAME | D13: Prefix | E13: Name | F13: Label(KO) | G13: Label(EN) | H13: Label Role | I13: DataType | J13: Period
B14: [D827580] 17. 우발채무 및 약정사항 | 17. Contingencies and Commitments | C14: 출자 약정의 세부사항에 대한 공시 | D14: dart | E14: EquityContributionsInCashBetweenEntityRelatedPartyContribution | F14: 출자액 | G14: capital contribution | H14: http://www.xbrl.org/2003/role/verboseLabel | I14: monetaryItemType | J14: INSTANT
B15: [D827580] 17. 우발채무 및 약정사항 | 17. Contingencies and Commitments | C15: 출자 약정의 세부사항에 대한 공시 | D15: dart | E15: EquityContributionsInCashBetweenEntityRelatedPartyWithdrawal | F15: 회수액 | G15: capital withdrawal | H15: http://www.xbrl.org/2003/role/verboseLabel | I15: monetaryItemType | J15: INSTANT
B16: [D827585] 17. 우발채무 및 약정사항 | 17. Contingencies and Commitments | C16: 출자 약정의 세부사항에 대한 공시 | D16: dart | E16: EquityContributionsInCashBetweenEntityRelatedPartyContribution | F16: 출자액 | G16: capital contribution | H16: http://www.xbrl.org/2003/role/verboseLabel | I16: monetaryItemType | J16: INSTANT
B17: [D827585] 17. 우발채무 및 약정사항 | 17. Contingencies and Commitments | C17: 출자 약정의 세부사항에 대한 공시 | D17: dart | E17: EquityContributionsInCashBetweenEntityRelatedPartyWithdrawal | F17: 회수액 | G17: capital withdrawal | H17: http://www.xbrl.org/2003/role/verboseLabel | I17: monetaryItemType | J17: INSTANT

Sheet Checklist_5-1
B2: 이자율, 할인율 속성 검토
B3: ※ XBRL Checklist 결과는 참고 목적으로 제공드리는 내역으로, 텍사노미 구조와 관련된 리뷰는 CoE 업무 Scope에 포함되지 않습니다.
L4: Reference - 금감원 가이드 151page
B11: =COUNTA(B14:B1048576) -> 0 | C11: 개 항목이 추출되었습니다.
B13: Role Definition | C13: TABLE NAME | D13: Prefix | E13: Name | F13: Label(KO) | G13: Label(EN) | H13: Label Role | I13: DataType | J13: Period
B14: [D822100] 12-1. 유형자산 | 12-1. Property, plant and equipment | C14: 자본화된 차입원가에 대한 공시 | D14: ifrs-full | E14: CapitalisationRateOfBorrowingCostsEligibleForCapitalisation | F14: 자본화가능차입원가를 산정하기 위하여 사용된 자본화이자율 | G14: Capitalisation rate of borrowing costs eligible for capitalisation | H14: http://www.xbrl.org/2003/role/label | I14: percentItemType | J14: DURATION
B15: [D822380] 30-1. 재무위험관리 | 30-1. Financial Risk Management | C15: 충당금 설정률표에 대한 공시 | D15: ifrs-full | E15: ExpectedCreditLossRate | F15: 기대손실율 | G15: Expected credit loss rate | H15: http://www.xbrl.org/2003/role/terseLabel | I15: percentItemType | J15: INSTANT
B16: [D822380] 30-1. 재무위험관리 | 30-1. Financial Risk Management | C16: 충당금 설정률표에 대한 공시_합계 | D16: ifrs-full | E16: ExpectedCreditLossRate | F16: 기대손실율 | G16: Expected credit loss rate | H16: http://www.xbrl.org/2003/role/terseLabel | I16: percentItemType | J16: INSTANT
B17: [D822380] 30-1. 재무위험관리 | 30-1. Financial Risk Management | C17: 자본위험관리에 대한 공시 | D17: entity00149655 | E17: DebtRatioABOfDisclosureOfCapitalRiskManagementOfDisclosureOfCapitalRiskManagementTableOfItems | F17: 부채비율(A/B) | G17: Debt ratio (A/B) | H17: http://www.xbrl.org/2003/role/label | I17: percentItemType | J17: INSTANT
B18: [D822385] 30-1. 재무위험관리 | 30-1. Financial Risk Management | C18: 충당금 설정률표에 대한 공시 | D18: ifrs-full | E18: ExpectedCreditLossRate | F18: 기대손실율 | G18: Expected credit loss rate | H18: http://www.xbrl.org/2003/role/terseLabel | I18: percentItemType | J18: INSTANT
B19: [D822385] 30-1. 재무위험관리 | 30-1. Financial Risk Management | C19: 충당금 설정률표에 대한 공시_합계 | D19: ifrs-full | E19: ExpectedCreditLossRate | F19: 기대손실율 | G19: Expected credit loss rate | H19: http://www.xbrl.org/2003/role/terseLabel | I19: percentItemType | J19: INSTANT
B20: [D822385] 30-1. 재무위험관리 | 30-1. Financial Risk Management | C20: 자본위험관리에 대한 공시 | D20: entity00149655 | E20: DebtRatioABOfDisclosureOfCapitalRiskManagementOfDisclosureOfCapitalRiskManagementTableOfItems | F20: 부채비율(A/B) | G20: Debt ratio (A/B) | H20: http://www.xbrl.org/2003/role/label | I20: percentItemType | J20: INSTANT
B21: [D822390] 10. 공정가치 측정 금융자산 | 10. Financial Assets Measured at Fair Value | C21: 당기손익-공정가치 측정 지분상품의 공정가치측정에 대한 공시 | D21: ifrs-full | E21: PercentageOfVotingEquityInterestsAcquired | F21: 지분율 | G21: Percentage of ownership | H21: http://www.xbrl.org/2003/role/terseLabel | I21: percentItemType | J21: INSTANT
B22: [D822390] 10. 공정가치 측정 금융자산 | 10. Financial Assets Measured at Fair Value | C22: 기타포괄손익-공정가치 측정 금융자산 상장주식 세부 보유내역에 대한 공시 | D22: ifrs-full | E22: PercentageOfVotingEquityInterestsAcquired | F22: 지분율 | G22: Percentage of ownership | H22: http://www.xbrl.org/2003/role/terseLabel | I22: percentItemType | J22: INSTANT
B23: [D822390] 10. 공정가치 측정 금융자산 | 10. Financial Assets Measured at Fair Value | C23: 기타포괄손익-공정가치 측정 금융자산 비상장주식 세부 보유내역에 대한 공시 | D23: ifrs-full | E23: PercentageOfVotingEquityInterestsAcquired | F23: 지분율 | G23: Percentage of ownership | H23: http://www.xbrl.org/2003/role/terseLabel | I23: percentItemType | J23: INSTANT
B24: [D822395] 10. 공정가치 측정 금융자산 | 10. Financial Assets Measured at Fair Value | C24: 당기손익-공정가치 측정 지분상품의 공정가치측정에 대한 공시 | D24: ifrs-full | E24: PercentageOfVotingEquityInterestsAcquired | F24: 지분율 | G24: Percentage of ownership | H24: http://www.xbrl.org/2003/role/terseLabel | I24: percentItemType | J24: INSTANT
... B78: [D861305] 20. 이익잉여금 | 20. Separated retained earnings | C78: 이익잉여금 처분계산서 | D78: dart | E78: DividendsRateforPreferredSharesPerShare | F78: 우선주 주당 배당률 | G78: Dividends rate for preferred shares per share | H78: http://www.xbrl.org/2003/role/label | I78: percentItemType | J78: DURATION

Sheet Checklist_5-2
B2: 주식 수 속성 검토
B3: ※ XBRL Checklist 결과는 참고 목적으로 제공드리는 내역으로, 텍사노미 구조와 관련된 리뷰는 CoE 업무 Scope에 포함되지 않습니다.
L4: Reference - 금감원 가이드 151page
B11: =COUNTA(B14:B1048576) -> 0 | C11: 개 항목이 추출되었습니다.
B13: Role Definition | C13: TABLE NAME | D13: Prefix | E13: Name | F13: Label(KO) | G13: Label(EN) | H13: Label Role | I13: DataType | J13: Period
B14: [D822390] 10. 공정가치 측정 금융자산 | 10. Financial Assets Measured at Fair Value | C14: 당기손익-공정가치 측정 지분상품의 공정가치측정에 대한 공시 | D14: entity00149655 | E14: NumberOfSharesOwnedOfDisclosureOfFairValueMeasurementOfEquityLineItemsOfDisclosureOfFairValueMeasurementOfEquityTableOfItems | F14: 보유주식수(단위: 주) | G14: Number of shares owned(Unit: share) | H14: http://www.xbrl.org/2003/role/terseLabel | I14: sharesItemType | J14: DURATION
B15: [D822390] 10. 공정가치 측정 금융자산 | 10. Financial Assets Measured at Fair Value | C15: 기타포괄손익-공정가치 측정 금융자산 상장주식 세부 보유내역에 대한 공시 | D15: entity00149655 | E15: NumberOfSharesOwnedOfDetailsNameOfFinancialAssetsAtFairValueThroughComprehensiveIncomeLineItemsOfDetailsOfListedFinancialAssetsAtFairValueThroughOtherComprehensiveIncomeTableTableOfItems | F15: 보유주식수(단위: 주) | G15: Number of shares owned(Unit: share) | H15: http://www.xbrl.org/2003/role/terseLabel | I15: sharesItemType | J15: DURATION
B16: [D822390] 10. 공정가치 측정 금융자산 | 10. Financial Assets Measured at Fair Value | C16: 기타포괄손익-공정가치 측정 금융자산 비상장주식 세부 보유내역에 대한 공시 | D16: entity00149655 | E16: NumberOfSharesOwnedOfDetailsNameOfFinancialAssetsAtFairValueThroughComprehensiveIncomeLineItemsOfDetailsOfNonListedFinancialAssetsAtFairValueThroughOtherComprehensiveIncomeTableOfItems | F16: 보유주식수(단위: 주) | G16: Number of shares owned(Unit: share) | H16: http://www.xbrl.org/2003/role/terseLabel | I16: sharesItemType | J16: DURATION
B17: [D822395] 10. 공정가치 측정 금융자산 | 10. Financial Assets Measured at Fair Value | C17: 당기손익-공정가치 측정 지분상품의 공정가치측정에 대한 공시 | D17: entity00149655 | E17: NumberOfSharesOwnedOfDisclosureOfFairValueMeasurementOfEquityLineItemsOfDisclosureOfFairValueMeasurementOfEquityTableOfItems | F17: 보유주식수(단위: 주) | G17: Number of shares owned(Unit: share) | H17: http://www.xbrl.org/2003/role/terseLabel | I17: sharesItemType | J17: DURATION
B18: [D822395] 10. 공정가치 측정 금융자산 | 10. Financial Assets Measured at Fair Value | C18: 기타포괄손익-공정가치 측정 금융자산 상장주식 세부 보유내역에 대한 공시 | D18: entity00149655 | E18: NumberOfSharesOwnedOfDetailsNameOfFinancialAssetsAtFairValueThroughComprehensiveIncomeLineItemsOfDetailsOfListedFinancialAssetsAtFairValueThroughOtherComprehensiveIncomeTableTableOfItems | F18: 보유주식수(단위: 주) | G18: Number of shares owned(Unit: share) | H18: http://www.xbrl.org/2003/role/terseLabel | I18: sharesItemType | J18: DURATION
B19: [D822395] 10. 공정가치 측정 금융자산 | 10. Financial Assets Measured at Fair Value | C19: 기타포괄손익-공정가치 측정 금융자산 비상장주식 세부 보유내역에 대한 공시 | D19: entity00149655 | E19: NumberOfSharesOwnedOfDetailsNameOfFinancialAssetsAtFairValueThroughComprehensiveIncomeLineItemsOfDetailsOfNonListedFinancialAssetsAtFairValueThroughOtherComprehensiveIncomeTableOfItems | F19: 보유주식수(단위: 주) | G19: Number of shares owned(Unit: share) | H19: http://www.xbrl.org/2003/role/terseLabel | I19: sharesItemType | J19: DURATION
B20: [D838000] 26. 주당순이익 | 26. Earnings per Share | C20: 주당이익 | D20: ifrs-full | E20: WeightedAverageShares | F20: 가중평균유통보통주식수(단위:주) | G20: Weighted average number of ordinary shares used in calculating basic earnings per share(Unit:shares) | H20: http://www.xbrl.org/2003/role/terseLabel | I20: sharesItemType | J20: DURATION
B21: [D838000] 26. 주당순이익 | 26. Earnings per Share | C21: 주당이익 | D21: ifrs-full | E21: WeightedAverageNumberOfInstrumentsUsedInCalculatingBasicEarningsLossPerInstrumentParticipatingEquityInstrumentsOtherThanOrdinaryShares | F21: 가중평균유통우선주식수(단위:주) | G21: Weighted average number of preferred shares outstanding(Unit: share) | H21: http://www.xbrl.org/2003/role/terseLabel | I21: sharesItemType | J21: DURATION
B22: [D838005] 26. 주당순이익 | 26. Earnings per Share | C22: 주당이익 | D22: ifrs-full | E22: WeightedAverageShares | F22: 가중평균유통보통주식수(단위:주) | G22: Weighted average number of ordinary shares used in calculating basic earnings per share(Unit:shares) | H22: http://www.xbrl.org/2003/role/terseLabel | I22: sharesItemType | J22: DURATION
B23: [D838005] 26. 주당순이익 | 26. Earnings per Share | C23: 주당이익 | D23: ifrs-full | E23: WeightedAverageNumberOfInstrumentsUsedInCalculatingBasicEarningsLossPerInstrumentParticipatingEquityInstrumentsOtherThanOrdinaryShares | F23: 가중평균유통우선주식수(단위:주) | G23: Weighted average number of preferred shares outstanding(Unit: share) | H23: http://www.xbrl.org/2003/role/terseLabel | I23: sharesItemType | J23: DURATION

Sheet Checklist_5-3
B2: 이연법인세부채(자산) 검토
B3: ※ XBRL Checklist 결과는 참고 목적으로 제공드리는 내역으로, 텍사노미 구조와 관련된 리뷰는 CoE 업무 Scope에 포함되지 않습니다.
L4: Reference - 금감원 가이드 253page
B11: =COUNTA(B14:B1048576) -> 0 | C11: 개 항목이 추출되었습니다.
B13: Role Definition | C13: TABLE NAME | D13: Prefix | E13: Name | F13: Label(KO) | G13: Label(EN) | H13: Label Role | I13: DataType | J13: Period
B14: [D835110] 25. 법인세비용 | 25. Income Tax Expense | C14: 일시적차이, 미사용 세무상 결손금과 미사용 세액공제에 대한 공시 | D14: ifrs-full | E14: DeferredTaxLiabilityAsset | F14: 기초 이연법인세부채(자산) | G14: Deferred tax liability (asset) at beginning of period | H14: http://www.xbrl.org/2003/role/periodStartLabel | I14: monetaryItemType | J14: INSTANT
B15: [D835110] 25. 법인세비용 | 25. Income Tax Expense | C15: 일시적차이, 미사용 세무상 결손금과 미사용 세액공제에 대한 공시 | D15: ifrs-full | E15: DeferredTaxLiabilityAsset | F15: 기말 이연법인세부채(자산) | G15: Deferred tax liability (asset) at Ending of period | H15: http://www.xbrl.org/2003/role/periodEndLabel | I15: monetaryItemType | J15: INSTANT
B16: [D835110] 25. 법인세비용 | 25. Income Tax Expense | C16: 일시적차이, 미사용 세무상 결손금과 미사용 세액공제에 대한 공시 합계 | D16: ifrs-full | E16: DeferredTaxLiabilityAsset | F16: 기초 이연법인세부채(자산) | G16: Deferred tax liability (asset) at beginning of period | H16: http://www.xbrl.org/2003/role/periodStartLabel | I16: monetaryItemType | J16: INSTANT
B17: [D835110] 25. 법인세비용 | 25. Income Tax Expense | C17: 일시적차이, 미사용 세무상 결손금과 미사용 세액공제에 대한 공시 합계 | D17: ifrs-full | E17: DeferredTaxLiabilityAsset | F17: 기말 이연법인세부채(자산) | G17: Deferred tax liability (asset) at Ending of period | H17: http://www.xbrl.org/2003/role/periodEndLabel | I17: monetaryItemType | J17: INSTANT
B18: [D835110] 25. 법인세비용 | 25. Income Tax Expense | C18: 일시적차이, 미사용 세무상 결손금과 미사용 세액공제에 대한 공시 합계3 | D18: ifrs-full | E18: DeferredTaxLiabilityAsset | F18: 기초 이연법인세부채(자산) | G18: Deferred tax liability (asset) at beginning of period | H18: http://www.xbrl.org/2003/role/periodStartLabel | I18: monetaryItemType | J18: INSTANT
B19: [D835110] 25. 법인세비용 | 25. Income Tax Expense | C19: 일시적차이, 미사용 세무상 결손금과 미사용 세액공제에 대한 공시 합계3 | D19: ifrs-full | E19: DeferredTaxLiabilityAsset | F19: 기말 이연법인세부채(자산) | G19: Deferred tax liability (asset) at Ending of period | H19: http://www.xbrl.org/2003/role/periodEndLabel | I19: monetaryItemType | J19: INSTANT
B20: [D835115] 25. 법인세비용 | 25. Income Tax Expense | C20: 일시적차이, 미사용 세무상 결손금과 미사용 세액공제에 대한 공시 | D20: ifrs-full | E20: DeferredTaxLiabilityAsset | F20: 기초 이연법인세부채(자산) | G20: Deferred tax liability (asset) at beginning of period | H20: http://www.xbrl.org/2003/role/periodStartLabel | I20: monetaryItemType | J20: INSTANT
B21: [D835115] 25. 법인세비용 | 25. Income Tax Expense | C21: 일시적차이, 미사용 세무상 결손금과 미사용 세액공제에 대한 공시 | D21: ifrs-full | E21: DeferredTaxLiabilityAsset | F21: 기말 이연법인세부채(자산) | G21: Deferred tax liability (asset) at Ending of period | H21: http://www.xbrl.org/2003/role/periodEndLabel | I21: monetaryItemType | J21: INSTANT
B22: [D835115] 25. 법인세비용 | 25. Income Tax Expense | C22: 일시적차이, 미사용 세무상 결손금과 미사용 세액공제에 대한 공시 합계 | D22: ifrs-full | E22: DeferredTaxLiabilityAsset | F22: 기초 이연법인세부채(자산) | G22: Deferred tax liability (asset) at beginning of period | H22: http://www.xbrl.org/2003/role/periodStartLabel | I22: monetaryItemType | J22: INSTANT
B23: [D835115] 25. 법인세비용 | 25. Income Tax Expense | C23: 일시적차이, 미사용 세무상 결손금과 미사용 세액공제에 대한 공시 합계 | D23: ifrs-full | E23: DeferredTaxLiabilityAsset | F23: 기말 이연법인세부채(자산) | G23: Deferred tax liability (asset) at Ending of period | H23: http://www.xbrl.org/2003/role/periodEndLabel | I23: monetaryItemType | J23: INSTANT
B24: [D835115] 25. 법인세비용 | 25. Income Tax Expense | C24: 일시적차이, 미사용 세무상 결손금과 미사용 세액공제에 대한 공시 합계3 | D24: ifrs-full | E24: DeferredTaxLiabilityAsset | F24: 기초 이연법인세부채(자산) | G24: Deferred tax liability (asset) at beginning of period | H24: http://www.xbrl.org/2003/role/periodStartLabel | I24: monetaryItemType | J24: INSTANT
B25: [D835115] 25. 법인세비용 | 25. Income Tax Expense | C25: 일시적차이, 미사용 세무상 결손금과 미사용 세액공제에 대한 공시 합계3 | D25: ifrs-full | E25: DeferredTaxLiabilityAsset | F25: 기말 이연법인세부채(자산) | G25: Deferred tax liability (asset) at Ending of period | H25: http://www.xbrl.org/2003/role/periodEndLabel | I25: monetaryItemType | J25: INSTANT

Sheet Checklist_5-4
B2: 기본주당이익/희석주당이익 속성 검토
B3: ※ XBRL Checklist 결과는 참고 목적으로 제공드리는 내역으로, 텍사노미 구조와 관련된 리뷰는 CoE 업무 Scope에 포함되지 않습니다.
L4: Reference - 금감원 가이드 259page
B11: =COUNTA(B14:B1048576) -> 0 | C11: 개 항목이 추출되었습니다.
B13: Role Definition | C13: TABLE NAME | D13: Prefix | E13: Name | F13: Label(KO) | G13: Label(EN) | H13: Label Role | I13: DataType | J13: Period

Sheet Checklist_5-5
B2: 기초/기말 영문명 검토
B3: ※ XBRL Checklist 결과는 참고 목적으로 제공드리는 내역으로, 텍사노미 구조와 관련된 리뷰는 CoE 업무 Scope에 포함되지 않습니다.
B11: =COUNTA(B14:B1048576) -> 0 | C11: 개 항목이 추출되었습니다.
B13: Role Definition | C13: TABLE NAME | D13: Prefix | E13: Name | F13: Label(KO) | G13: Label(EN) | H13: Label Role | I13: DataType | J13: Period
B14: [D520000] 현금흐름표, 간접법 - 연결 | Statement of cash flows, indirect method - Consolidated financial statements | C14: [D520000] 현금흐름표, 간접법 - 연결 | D14: dart | E14: CashAndCashEquivalentsAtBeginningOfPeriodCf | F14: 기초의 현금및현금성자산 | G14: Cash and cash equivalents at beginning of period | H14: http://www.xbrl.org/2003/role/terseLabel | I14: monetaryItemType | J14: INSTANT
B15: [D520000] 현금흐름표, 간접법 - 연결 | Statement of cash flows, indirect method - Consolidated financial statements | C15: [D520000] 현금흐름표, 간접법 - 연결 | D15: dart | E15: CashAndCashEquivalentsAtEndOfPeriodCf | F15: 기말의 현금및현금성자산 | G15: Cash and cash equivalents at end of period | H15: http://www.xbrl.org/2003/role/terseLabel | I15: monetaryItemType | J15: INSTANT
B16: [D520005] 현금흐름표, 간접법 - 별도 | Statement of cash flows, indirect method - Separate financial statements | C16: [D520005] 현금흐름표, 간접법 - 별도 | D16: dart | E16: CashAndCashEquivalentsAtBeginningOfPeriodCf | F16: 기초의 현금및현금성자산 | G16: Cash and cash equivalents at beginning of period | H16: http://www.xbrl.org/2003/role/terseLabel | I16: monetaryItemType | J16: INSTANT
B17: [D520005] 현금흐름표, 간접법 - 별도 | Statement of cash flows, indirect method - Separate financial statements | C17: [D520005] 현금흐름표, 간접법 - 별도 | D17: dart | E17: CashAndCashEquivalentsAtEndOfPeriodCf | F17: 기말의 현금및현금성자산 | G17: Cash and cash equivalents at end of period | H17: http://www.xbrl.org/2003/role/terseLabel | I17: monetaryItemType | J17: INSTANT
B18: [D610000] 자본변동표 - 연결 | Statement of changes in equity - Consolidated financial statements | C18: [D610000] 자본변동표 - 연결 | D18: dart | E18: EquityAtBeginningOfPeriod | F18: 보고금액 | G18: Equity at beginning of period | H18: http://www.xbrl.org/2003/role/terseLabel | I18: monetaryItemType | J18: DURATION
B19: [D610000] 자본변동표 - 연결 | Statement of changes in equity - Consolidated financial statements | C19: [D610000] 자본변동표 - 연결 | D19: ifrs-full | E19: Equity | F19: 기말자본 | G19: Equity at end of period | H19: http://www.xbrl.org/2003/role/periodEndLabel | I19: monetaryItemType | J19: INSTANT
B20: [D610000] 자본변동표 - 연결 | Statement of changes in equity - Consolidated financial statements | C20: [D610000] 자본변동표 - 연결 | D20: dart | E20: EquityAtBeginningOfPeriod | F20: 보고금액 | G20: Equity at beginning of period | H20: http://www.xbrl.org/2003/role/terseLabel | I20: monetaryItemType | J20: DURATION
B21: [D610000] 자본변동표 - 연결 | Statement of changes in equity - Consolidated financial statements | C21: [D610000] 자본변동표 - 연결 | D21: ifrs-full | E21: Equity | F21: 기말자본 | G21: Equity at end of period | H21: http://www.xbrl.org/2003/role/periodEndLabel | I21: monetaryItemType | J21: INSTANT
B22: [D610000] 자본변동표 - 연결 | Statement of changes in equity - Consolidated financial statements | C22: [D610000] 자본변동표 - 연결 | D22: dart | E22: EquityAtBeginningOfPeriod | F22: 보고금액 | G22: Equity at beginning of period | H22: http://www.xbrl.org/2003/role/terseLabel | I22: monetaryItemType | J22: DURATION
B23: [D610000] 자본변동표 - 연결 | Statement of changes in equity - Consolidated financial statements | C23: [D610000] 자본변동표 - 연결 | D23: ifrs-full | E23: Equity | F23: 기말자본 | G23: Equity at end of period | H23: http://www.xbrl.org/2003/role/periodEndLabel | I23: monetaryItemType | J23: INSTANT
B24: [D610005] 자본변동표 - 별도 | Statement of changes in equity - Separate financial statements | C24: [D610005] 자본변동표 - 별도 | D24: dart | E24: EquityAtBeginningOfPeriod | F24: 보고금액 | G24: Equity at beginning of period | H24: http://www.xbrl.org/2003/role/terseLabel | I24: monetaryItemType | J24: DURATION
... B112: [D851105] 28. 현금흐름표 | 28. Separated Statements of Cash Flows | C112: 재무활동현금흐름 | D112: ifrs-full | E112: LiabilitiesArisingFromFinancingActivities | F112: 재무활동에서 생기는 기말 부채 | G112: Liabilities arising from financing activities at ending of period | H112: http://www.xbrl.org/2003/role/periodEndLabel | I112: monetaryItemType | J112: INSTANT

Sheet Checklist_6-1
B2: 축 확장 검토
B3: ※ XBRL Checklist 결과는 참고 목적으로 제공드리는 내역으로, 텍사노미 구조와 관련된 리뷰는 CoE 업무 Scope에 포함되지 않습니다.
B11: =COUNTA(B14:B1048576) -> 0 | C11: 개 항목이 추출되었습니다.
B13: Role Definition | C13: TABLE NAME | D13: Prefix | E13: Name | F13: Label(KO) | G13: Label(EN) | H13: Label Role | I13: DataType | J13: Period

Sheet Checklist_6-2
B2: 멤버열 확장 검토
B3: ※ XBRL Checklist 결과는 참고 목적으로 제공드리는 내역으로, 텍사노미 구조와 관련된 리뷰는 CoE 업무 Scope에 포함되지 않습니다.
B11: =COUNTA(B14:B1048576) -> 0 | C11: 개 항목이 추출되었습니다.
B13: Role Definition | C13: TABLE NAME | D13: Prefix | E13: Name | F13: Label(KO) | G13: Label(EN) | H13: Label Role | I13: DataType | J13: Period

Sheet Checklist_6-3
B2: Duration / Instant 속성 검토
B3: ※ XBRL Checklist 결과는 참고 목적으로 제공드리는 내역으로, 텍사노미 구조와 관련된 리뷰는 CoE 업무 Scope에 포함되지 않습니다.
B11: =COUNTA(B14:B1048576) -> 0 | C11: 개 항목이 추출되었습니다.
B13: Role Definition | C13: TABLE NAME | D13: Prefix | E13: Name | F13: Label(KO) | G13: Label(EN) | H13: Label Role | I13: DataType | J13: Period
B14: [D210000] 재무상태표, 유동/비유동법 - 연결 | Statement of financial position, current/non-current - Consolidated financial statements | C14: [D210000] 재무상태표, 유동/비유동법 - 연결 | D14: entity00149655 | E14: udf_BS_202557165316OfCurrentLiabilities | F14: 단기차입금 | G14: Short-term borrowings | H14: http://www.xbrl.org/2003/role/label | I14: monetaryItemType | J14: INSTANT
B15: [D210005] 재무상태표, 유동/비유동법 - 별도 | Statement of financial position, current/non-current - Separate financial statements | C15: [D210005] 재무상태표, 유동/비유동법 - 별도 | D15: entity00149655 | E15: ShortTermBorrowingsOfCurrentLiabilities | F15: 단기차입금 | G15: Short-term borrowings | H15: http://www.xbrl.org/2003/role/label | I15: monetaryItemType | J15: INSTANT
B16: [D520000] 현금흐름표, 간접법 - 연결 | Statement of cash flows, indirect method - Consolidated financial statements | C16: [D520000] 현금흐름표, 간접법 - 연결 | D16: entity00149655 | E16: NetDecreaseInShortTermFinancialInstrumentsOfInflowsOfCashFromInvestingActivities | F16: 단기금융상품의 순감소 | G16: NetDecreaseInShortTermFinancialInstrumentsOfCashFlowsFromUsedInInvestingActivities | H16: http://www.xbrl.org/2003/role/label | I16: monetaryItemType | J16: DURATION
B17: [D520000] 현금흐름표, 간접법 - 연결 | Statement of cash flows, indirect method - Consolidated financial statements | C17: [D520000] 현금흐름표, 간접법 - 연결 | D17: entity00149655 | E17: NetReductionInCurrentFairValueMeasurementFinancialAssetsThroughGainsOrLossesOfInflowsOfCashFromInvestingActivities | F17: 유동성 당기손익-공정가치측정금융자산의 순감소 | G17: Net reduction in Current fair value measurement financial assets through gains or losses | H17: http://www.xbrl.org/2003/role/label | I17: monetaryItemType | J17: DURATION
B18: [D520000] 현금흐름표, 간접법 - 연결 | Statement of cash flows, indirect method - Consolidated financial statements | C18: [D520000] 현금흐름표, 간접법 - 연결 | D18: entity00149655 | E18: DecreaseInOtherNonCurrentAssetsOfInflowsOfCashFromInvestingActivities | F18: 기타비유동자산의 감소 | G18: Decrease in other non-current assets | H18: http://www.xbrl.org/2003/role/label | I18: monetaryItemType | J18: DURATION
B19: [D520000] 현금흐름표, 간접법 - 연결 | Statement of cash flows, indirect method - Consolidated financial statements | C19: [D520000] 현금흐름표, 간접법 - 연결 | D19: entity00149655 | E19: NetincreaseinshorttermfinancialinstrumentsofcashflowsfromusedininvestingactivitiesOfOutflowsOfCashFromInvestingActivities | F19: 단기금융상품의 순증가 | G19: NetIncreaseInShortTermFinancialInstrumentsOfCashFlowsFromUsedInInvestingActivities | H19: http://www.xbrl.org/2009/role/negatedLabel | I19: monetaryItemType | J19: DURATION
B20: [D520000] 현금흐름표, 간접법 - 연결 | Statement of cash flows, indirect method - Consolidated financial statements | C20: [D520000] 현금흐름표, 간접법 - 연결 | D20: entity00149655 | E20: IncreaseOfOtherNonCurrentAssetsOfudf_CF_202542922242642OfCashFlowsFromUsedInInvestingActivities | F20: 기타비유동자산의 증가 | G20: Increase of other non-current assets | H20: http://www.xbrl.org/2009/role/negatedLabel | I20: monetaryItemType | J20: DURATION
B21: [D520000] 현금흐름표, 간접법 - 연결 | Statement of cash flows, indirect method - Consolidated financial statements | C21: [D520000] 현금흐름표, 간접법 - 연결 | D21: entity00149655 | E21: InflowsOfCashFromFinancingActivitiesOfCashFlowsFromUsedInFinancingActivities | F21: 재무활동으로 인한 현금유입액 | G21: Inflows of cash from financing activities | H21: http://www.xbrl.org/2003/role/label | I21: monetaryItemType | J21: DURATION
B22: [D520000] 현금흐름표, 간접법 - 연결 | Statement of cash flows, indirect method - Consolidated financial statements | C22: [D520000] 현금흐름표, 간접법 - 연결 | D22: entity00149655 | E22: ProceedsFromOtherEquityOfInflowsOfCashFromFinancingActivitiesOfCashflowsOfInflowsOfCashFromFinancingActivitiesOfCashFlowsFromUsedInFinancingActivities | F22: 기타자본의 증가 | G22: Proceeds From Other Equity Of Inflows Of Cash From Financing Activities Of CashFlows | H22: http://www.xbrl.org/2003/role/label | I22: monetaryItemType | J22: DURATION
B23: [D520000] 현금흐름표, 간접법 - 연결 | Statement of cash flows, indirect method - Consolidated financial statements | C23: [D520000] 현금흐름표, 간접법 - 연결 | D23: entity00149655 | E23: OutflowsOfCashFromFinancingActivitiesOfCashFlowsFromUsedInFinancingActivities | F23: 재무활동으로 인한 현금유출액 | G23: Outflows of cash from financing activities | H23: http://www.xbrl.org/2009/role/negatedLabel | I23: monetaryItemType | J23: DURATION
B24: [D520000] 현금흐름표, 간접법 - 연결 | Statement of cash flows, indirect method - Consolidated financial statements | C24: [D520000] 현금흐름표, 간접법 - 연결 | D24: entity00149655 | E24: NetDecreaseInShortTermBorrowingsOfOutflowsOfCashFromFinancingActivitiesOfCashFlowsFromUsedInFinancingActivities | F24: 단기차입금의 순감소 | G24: Net decrease in short-term borrowings | H24: http://www.xbrl.org/2009/role/negatedLabel | I24: monetaryItemType | J24: DURATION
... B612: [D871100] 29. 영업부문 | 29. Segment Information | C612: 지역에 대한 공시, 합계2 | D612: entity00149655 | E612: DisclosureOfGeographicalAreasTotal2OfDisclosureOfGeographicalAreasTotal2TableOfLineItems | F612: 지역에 대한 공시, 합계2 | G612: Disclosure of geographical areas_total2 | H612: http://www.xbrl.org/2003/role/label | I612: stringItemType | J612: DURATION

Sheet Checklist_7-1
B2: Negate 검토
B3: ※ XBRL Checklist 결과는 참고 목적으로 제공드리는 내역으로, 텍사노미 구조와 관련된 리뷰는 CoE 업무 Scope에 포함되지 않습니다.
B11: =COUNTA(B14:B1048576) -> 0 | C11: 개 항목이 추출되었습니다.
B13: Role Definition | C13: TABLE NAME | D13: Prefix | E13: Name | F13: Label(KO) | G13: Label(EN) | H13: Label Role | I13: DataType | J13: Period | K13: Negate_표준 | L13: Negate_사용자지정
B14: [D520000] 현금흐름표, 간접법 - 연결 | Statement of cash flows, indirect method - Consolidated financial statements | C14: [D520000] 현금흐름표, 간접법 - 연결 | D14: ifrs-full | E14: OutflowsOfCashFromInvestingActivities | F14: 투자활동으로 인한 현금유출액 | G14: Outflows of cash from investing activities | H14: http://www.xbrl.org/2009/role/negatedLabel | I14: monetaryItemType | J14: DURATION | K14: - | L14: negate
B15: [D520000] 현금흐름표, 간접법 - 연결 | Statement of cash flows, indirect method - Consolidated financial statements | C15: [D520000] 현금흐름표, 간접법 - 연결 | D15: entity00149655 | E15: NetincreaseinshorttermfinancialinstrumentsofcashflowsfromusedininvestingactivitiesOfOutflowsOfCashFromInvestingActivities | F15: 단기금융상품의 순증가 | G15: NetIncreaseInShortTermFinancialInstrumentsOfCashFlowsFromUsedInInvestingActivities | H15: http://www.xbrl.org/2009/role/negatedLabel | I15: monetaryItemType | J15: DURATION | K15: - | L15: negate
B16: [D520000] 현금흐름표, 간접법 - 연결 | Statement of cash flows, indirect method - Consolidated financial statements | C16: [D520000] 현금흐름표, 간접법 - 연결 | D16: entity00149655 | E16: IncreaseOfOtherNonCurrentAssetsOfudf_CF_202542922242642OfCashFlowsFromUsedInInvestingActivities | F16: 기타비유동자산의 증가 | G16: Increase of other non-current assets | H16: http://www.xbrl.org/2009/role/negatedLabel | I16: monetaryItemType | J16: DURATION | K16: - | L16: negate
B17: [D520000] 현금흐름표, 간접법 - 연결 | Statement of cash flows, indirect method - Consolidated financial statements | C17: [D520000] 현금흐름표, 간접법 - 연결 | D17: entity00149655 | E17: OutflowsOfCashFromFinancingActivitiesOfCashFlowsFromUsedInFinancingActivities | F17: 재무활동으로 인한 현금유출액 | G17: Outflows of cash from financing activities | H17: http://www.xbrl.org/2009/role/negatedLabel | I17: monetaryItemType | J17: DURATION | K17: - | L17: negate
B18: [D520000] 현금흐름표, 간접법 - 연결 | Statement of cash flows, indirect method - Consolidated financial statements | C18: [D520000] 현금흐름표, 간접법 - 연결 | D18: ifrs-full | E18: DividendsPaidToEquityHoldersOfParentClassifiedAsFinancingActivities | F18: 배당금의 지급 | G18: Dividends paid to equity holders of parent, classified as financing activities | H18: http://www.xbrl.org/2009/role/negatedTerseLabel | I18: monetaryItemType | J18: DURATION | K18: - | L18: negate
B19: [D520000] 현금흐름표, 간접법 - 연결 | Statement of cash flows, indirect method - Consolidated financial statements | C19: [D520000] 현금흐름표, 간접법 - 연결 | D19: entity00149655 | E19: NetDecreaseInShortTermBorrowingsOfOutflowsOfCashFromFinancingActivitiesOfCashFlowsFromUsedInFinancingActivities | F19: 단기차입금의 순감소 | G19: Net decrease in short-term borrowings | H19: http://www.xbrl.org/2009/role/negatedLabel | I19: monetaryItemType | J19: DURATION | K19: - | L19: negate
B20: [D520000] 현금흐름표, 간접법 - 연결 | Statement of cash flows, indirect method - Consolidated financial statements | C20: [D520000] 현금흐름표, 간접법 - 연결 | D20: entity00149655 | E20: RepaymentsOfCurrentPortionOfLongTermTradePayablesOfOutflowsOfCashFromFinancingActivitiesOfCashFlowsFromUsedInFinancingActivities | F20: 유동성장기채무의 상환 | G20: Repayments of current portion of long-term trade payables | H20: http://www.xbrl.org/2009/role/negatedLabel | I20: monetaryItemType | J20: DURATION | K20: - | L20: negate
B21: [D520000] 현금흐름표, 간접법 - 연결 | Statement of cash flows, indirect method - Consolidated financial statements | C21: [D520000] 현금흐름표, 간접법 - 연결 | D21: entity00149655 | E21: AdditionalAcquisitionOfNonControllingInterestsOfOutflowsOfCashFromFinancingActivitiesOfCashFlowsFromUsedInFinancingActivities | F21: 비지배지분의 추가취득 | G21: Additional acquisition of non-controlling interests | H21: http://www.xbrl.org/2009/role/negatedLabel | I21: monetaryItemType | J21: DURATION | K21: - | L21: negate
B22: [D520000] 현금흐름표, 간접법 - 연결 | Statement of cash flows, indirect method - Consolidated financial statements | C22: [D520000] 현금흐름표, 간접법 - 연결 | D22: entity00149655 | E22: StockRedemptionOnNonControllingInterestsOfOutflowsOfCashFromFinancingActivitiesOfCashFlowsFromUsedInFinancingActivities | F22: 비지배지분에 대한 유상감자 | G22: Stock redemption on non-controlling interests | H22: http://www.xbrl.org/2009/role/negatedLabel | I22: monetaryItemType | J22: DURATION | K22: - | L22: negate
B23: [D520000] 현금흐름표, 간접법 - 연결 | Statement of cash flows, indirect method - Consolidated financial statements | C23: [D520000] 현금흐름표, 간접법 - 연결 | D23: ifrs-full | E23: DividendsPaidToNoncontrollingInterestsClassifiedAsFinancingActivities | F23: 비지배지분에 대한 배당 | G23: Dividends paid to non-controlling interests | H23: http://www.xbrl.org/2009/role/negatedTerseLabel | I23: monetaryItemType | J23: DURATION | K23: - | L23: negate
B24: [D831150] 4. 건설계약 등 | 4. Construction Contracts | C24: 하자보수충당부채와 공사손실충당부채에 대한 공시 | D24: entity00149655 | E24: DecreaseOfDisclosureOfOtherProvisionsLineItemsOfDisclosureOfProvisionsForConstructionWarrantiesAndConstructionLossesTableOfItems | F24: 감소액 | G24: Decrease | H24: http://www.xbrl.org/2009/role/negatedLabel | I24: monetaryItemType | J24: DURATION | K24: - | L24: negate
... B84: [D823005] 30-2. 공정가치측정 | 30-2. Fair value measurement | C84: 관측할 수 없는 투입변수의 변동으로 인한 공정가치측정의 민감도분석 공시, 자산 | D84: ifrs-full | E84: DecreaseInFairValueMeasurementDueToChangeInMultipleUnobservableInputsToReflectReasonablyPossibleAlternativeAssumptionsRecognisedInProfitOrLossBeforeTaxAssets | F84: 불리한 변동, 당기손익 | G84: Unfavorable changes, profit or loss | H84: http://www.xbrl.org/2009/role/negatedLabel | I84: monetaryItemType | J84: DURATION | K84: - | L84: negate
